ezautoml/__init__.py
ezautoml/__version__.py
ezautoml/cli.py
ezautoml/model.py
ezautoml/registry.py
ezautoml/data/loader.py
ezautoml/data/preprocess.py
ezautoml/evaluation/evaluator.py
ezautoml/evaluation/metric.py
ezautoml/evaluation/task.py
ezautoml/metalearning/features.py
ezautoml/optimization/optimizer.py
ezautoml/optimization/optimizers/optuna.py
ezautoml/optimization/optimizers/random_search.py
ezautoml/optimization/optimizers/smac.py
ezautoml/parsers/optuna.py
ezautoml/resources/__init__.py
ezautoml/resources/spaces/__init__.py
ezautoml/resources/spaces/classification_space.yaml
ezautoml/resources/spaces/regression_space.yaml
ezautoml/results/history.py
ezautoml/results/trial.py
ezautoml/scripts/generate_spaces.py
ezautoml/space/__init__.py
ezautoml/space/component.py
ezautoml/space/hyperparam.py
ezautoml/space/search_point.py
ezautoml/space/search_space.py
ezautoml/space/space.py
ezautoml-0.7.1.dist-info/licenses/LICENSE
ezautoml-0.7.1.dist-info/METADATA
ezautoml-0.7.1.dist-info/WHEEL
ezautoml-0.7.1.dist-info/entry_points.txt
ezautoml-0.7.1.dist-info/top_level.txt
ezautoml-0.7.1.dist-info/RECORD
