Metadata-Version: 2.4
Name: eZAutoML
Version: 0.7.1
Summary: A Democratized lightweight and transparent AutoML framework
Author-email: eZWALT <waltertv02@gmail.com>
License-Expression: BSD-3-Clause
Project-URL: Repository, https://github.com/eZWALT/eZAutoML
Project-URL: Issues, https://github.com/eZWALT/eZAutoML/issues
Classifier: Intended Audience :: Science/Research
Classifier: Intended Audience :: Developers
Classifier: Programming Language :: Python
Classifier: Operating System :: POSIX
Classifier: Operating System :: Unix
Classifier: Operating System :: MacOS
Classifier: Programming Language :: Python :: 3
Classifier: Programming Language :: Python :: 3.10
Classifier: Programming Language :: Python :: 3.11
Classifier: Programming Language :: Python :: 3.12
Requires-Python: >=3.10
License-File: LICENSE
Requires-Dist: scikit-learn
Requires-Dist: numpy
Requires-Dist: pandas
Requires-Dist: loguru
Requires-Dist: xgboost
Requires-Dist: catboost
Requires-Dist: lightgbm
Requires-Dist: rich
Provides-Extra: path-loaders
Requires-Dist: openpyxl; extra == "path-loaders"
Requires-Dist: pyarrow; extra == "path-loaders"
Dynamic: license-file
